intuned_client/__init__.py
intuned_client/_version.py
intuned_client/authsessions.py
intuned_client/basesdk.py
intuned_client/create.py
intuned_client/httpclient.py
intuned_client/jobs.py
intuned_client/project.py
intuned_client/py.typed
intuned_client/recorder.py
intuned_client/run.py
intuned_client/runs.py
intuned_client/sdk.py
intuned_client/sdkconfiguration.py
intuned_client/update.py
intuned_client/_hooks/__init__.py
intuned_client/_hooks/sdkhooks.py
intuned_client/_hooks/types.py
intuned_client/errors/__init__.py
intuned_client/errors/createjobop.py
intuned_client/errors/deletejobop.py
intuned_client/errors/getjobop.py
intuned_client/errors/getjobrunop.py
intuned_client/errors/getjobrunsop.py
intuned_client/errors/getjobsop.py
intuned_client/errors/intunedclientdefaulterror.py
intuned_client/errors/intunedclienterror.py
intuned_client/errors/no_response_error.py
intuned_client/errors/pausejobop.py
intuned_client/errors/responsevalidationerror.py
intuned_client/errors/resumejobop.py
intuned_client/errors/terminatejobrunop.py
intuned_client/errors/triggerjobop.py
intuned_client/models/__init__.py
intuned_client/models/createauthsessionresultop.py
intuned_client/models/createjobop.py
intuned_client/models/createorupdateauthsessionstartop.py
intuned_client/models/deleteauthsessionop.py
intuned_client/models/deletejobop.py
intuned_client/models/getauthsessionop.py
intuned_client/models/getauthsessionsop.py
intuned_client/models/getjobop.py
intuned_client/models/getjobrunop.py
intuned_client/models/getjobrunsop.py
intuned_client/models/getjobsop.py
intuned_client/models/pausejobop.py
intuned_client/models/resumejobop.py
intuned_client/models/runapiresultop.py
intuned_client/models/runapistartop.py
intuned_client/models/security.py
intuned_client/models/startauthsessionrecorderop.py
intuned_client/models/terminatejobrunop.py
intuned_client/models/triggerjobop.py
intuned_client/models/updateauthsessionresultop.py
intuned_client/models/updateauthsessionstartop.py
intuned_client-0.4.1.dist-info/METADATA
intuned_client-0.4.1.dist-info/WHEEL
intuned_client-0.4.1.dist-info/top_level.txt
intuned_client-0.4.1.dist-info/RECORD
